crystal_eyes/__init__.py
crystal_eyes/classifer.py
crystal_eyes/detector.py
crystal_eyes/displayer.py
crystal_eyes/utils.py
crystal_eyes/workplace.py
crystal_eyes-0.1.0.dist-info/WHEEL
crystal_eyes-0.1.0.dist-info/METADATA
crystal_eyes-0.1.0.dist-info/RECORD
