Metadata-Version: 2.1
Name: crystal-eyes
Version: 0.1.0
Summary: 
Author: KiyoshiMu
Author-email: mooyewtsing@gmail.com
Requires-Python: >=3.8,<4.0
Classifier: Programming Language :: Python :: 3
Classifier: Programming Language :: Python :: 3.8
Classifier: Programming Language :: Python :: 3.9
Requires-Dist: Pillow (>=8.0.1,<9.0.0)
Requires-Dist: fastapi (>=0.62.0,<0.63.0)
Requires-Dist: numpy (>=1.19.4,<2.0.0)
Requires-Dist: onnxruntime (>=1.6.0,<2.0.0)
Requires-Dist: python-multipart (>=0.0.5,<0.0.6)
Requires-Dist: uvicorn (>=0.13.2,<0.14.0)
